uk_bin_collection/README.rst
uk_bin_collection/tests/check_selenium_url_in_input.json.py
uk_bin_collection/tests/council_feature_input_parity.py
uk_bin_collection/tests/features/environment.py
uk_bin_collection/tests/features/validate_council_outputs.feature
uk_bin_collection/tests/input.json
uk_bin_collection/tests/output.schema
uk_bin_collection/tests/step_defs/step_helpers/file_handler.py
uk_bin_collection/tests/step_defs/test_validate_council.py
uk_bin_collection/tests/test_collect_data.py
uk_bin_collection/tests/test_common_functions.py
uk_bin_collection/tests/test_conftest.py
uk_bin_collection/tests/test_get_data.py
uk_bin_collection/uk_bin_collection/collect_data.py
uk_bin_collection/uk_bin_collection/common.py
uk_bin_collection/uk_bin_collection/councils/AberdeenCityCouncil.py
uk_bin_collection/uk_bin_collection/councils/AberdeenshireCouncil.py
uk_bin_collection/uk_bin_collection/councils/AdurAndWorthingCouncils.py
uk_bin_collection/uk_bin_collection/councils/AmberValleyBoroughCouncil.py
uk_bin_collection/uk_bin_collection/councils/AntrimAndNewtonabbeyCouncil.py
uk_bin_collection/uk_bin_collection/councils/ArdsAndNorthDownCouncil.py
uk_bin_collection/uk_bin_collection/councils/ArgyllandButeCouncil.py
uk_bin_collection/uk_bin_collection/councils/ArmaghBanbridgeCraigavonCouncil.py
uk_bin_collection/uk_bin_collection/councils/ArunCouncil.py
uk_bin_collection/uk_bin_collection/councils/AshfieldDistrictCouncil.py
uk_bin_collection/uk_bin_collection/councils/AshfordBoroughCouncil.py
uk_bin_collection/uk_bin_collection/councils/AylesburyValeCouncil.py
uk_bin_collection/uk_bin_collection/councils/BCPCouncil.py
uk_bin_collection/uk_bin_collection/councils/BaberghDistrictCouncil.py
uk_bin_collection/uk_bin_collection/councils/BarnetCouncil.py
uk_bin_collection/uk_bin_collection/councils/BarnsleyMBCouncil.py
uk_bin_collection/uk_bin_collection/councils/BasildonCouncil.py
uk_bin_collection/uk_bin_collection/councils/BasingstokeCouncil.py
uk_bin_collection_ar_fork_fix-0.137.1.dist-info/LICENSE
uk_bin_collection_ar_fork_fix-0.137.1.dist-info/METADATA
uk_bin_collection_ar_fork_fix-0.137.1.dist-info/WHEEL
uk_bin_collection_ar_fork_fix-0.137.1.dist-info/entry_points.txt
uk_bin_collection_ar_fork_fix-0.137.1.dist-info/RECORD
