Metadata-Version: 2.3
Name: uk_bin_collection_ar_fork_fix
Version: 0.137.1
Summary: Python Lib to collect UK Bin Data
Author: Robert Bradley
Author-email: robbrad182@gmail.com
Requires-Python: >=3.12,<3.14
Classifier: Programming Language :: Python :: 3
Classifier: Programming Language :: Python :: 3.12
Classifier: Programming Language :: Python :: 3.13
Requires-Dist: bs4
Requires-Dist: holidays
Requires-Dist: lxml
Requires-Dist: pandas
Requires-Dist: python-dateutil
Requires-Dist: requests
Requires-Dist: selenium
Requires-Dist: tabulate (>=0.9.0,<0.10.0)
Requires-Dist: urllib3
Requires-Dist: webdriver-manager (>=4.0.1,<5.0.0)
Project-URL: issues, https://github.com/robbrad/UKBinCollectionData/issues
